entrydir_pypath/__init__.py
entrydir_pypath/entrydir_pypath.py
entrydir_pypath-0.1.0.dev3.dist-info/DESCRIPTION.rst
entrydir_pypath-0.1.0.dev3.dist-info/METADATA
entrydir_pypath-0.1.0.dev3.dist-info/RECORD
entrydir_pypath-0.1.0.dev3.dist-info/WHEEL
entrydir_pypath-0.1.0.dev3.dist-info/entry_points.txt
entrydir_pypath-0.1.0.dev3.dist-info/metadata.json
entrydir_pypath-0.1.0.dev3.dist-info/top_level.txt
entrydir_pypath_config/__init__.py
entrydir_pypath_config/installer.py
