Metadata-Version: 2.0
Name: entrydir-pypath
Version: 0.1.0.dev3
Summary: Utility to set up sys.path for source-tree imports
Home-page: https://pypi.python.org/pypi/entrydir-pypath/
Author: Björn Samuelsson
Author-email: bjorn.samuelsson@anoto.com
License: ICS
Keywords: path import
Platform: UNKNOWN
Classifier: Development Status :: 2 - Pre-Alpha
Classifier: Topic :: Utilities
Classifier: Intended Audience :: Developers
Classifier: License :: OSI Approved :: ISC License (ISCL)
